LICENSE.txt
README.md
setup.cfg
setup.py
sightvision/__init__.py
sightvision.egg-info/PKG-INFO
sightvision.egg-info/SOURCES.txt
sightvision.egg-info/dependency_links.txt
sightvision.egg-info/not-zip-safe
sightvision.egg-info/requires.txt
sightvision.egg-info/top_level.txt
sightvision/common/__init__.py
sightvision/configuration/__init__.py
sightvision/configuration/constants.py
sightvision/module/__init__.py
sightvision/module/face_detection.py
sightvision/module/face_mesh.py
sightvision/module/hand_tracking.py
sightvision/module/pose_estimation.py
sightvision/utils/__init__.py
sightvision/utils/basics.py